[
  {
    "title": "japanese in your languages", 
    "url": "https://www.youtube.com/@japaneseinyourlanguages/videos", 
    "data": []
  }, 
  {
    "title": "Japanese Listening Shadowing", 
    "url": "https://www.youtube.com/@Japanese-listening-shadowiing/videos"},
  {
    "title": "Elsaの放送", 
    "url": "https://www.youtube.com/@ElsaJapanese/videos",
    "字幕": false
  },
  {
    "title": "海海日語新幹線", 
    "url": "https://www.youtube.com/@kai-Japanese-Shinkansen/videos",
    "data": []
  },
  {
    "title": "每日日語時刻", 
    "url": "https://www.youtube.com/@%E6%AF%8F%E6%97%A5%E6%97%A5%E8%AA%9E%E6%99%82%E5%88%BB/videos",
    "data": []
  },
  {
    "title": "mimi輕鬆聽日語", 
    "url": "https://www.youtube.com/@mimi%E8%BC%95%E9%AC%86%E8%81%BD%E6%97%A5%E8%AA%9E/videos",
    "data": []
  },
  {
    "title": "日文筆記本", 
    "url": "https://www.youtube.com/@nihongo-note/videos",
    "data": []
  },
  {
    "title": "30分鐘超集中聽日文", 
    "url": "https://www.youtube.com/@japanese30min/videos",
    "data": []
  },
  {
    "title": "日語達人養成所 | 聽得懂文法", 
    "url": "https://www.youtube.com/@JapaneseListeningPro/videos",
    "data": []
  },
  {
    "title": "IM 英日文", 
    "url": "https://www.youtube.com/@im_jp_en/videos",
    "data": []
  },
  {
    "title": "Sakura Japanese Cafe", 
    "url": "https://www.youtube.com/@SakuraJapaneseCafe/videos",
    "data": []
  },
  {
    "title": "Learn Japanese for beginners", 
    "url": "https://www.youtube.com/@JapaneseBeginnersChannel/videos",
    "data": []
  },
  {
    "title": "Wankoro的日语学习", 
    "url": "https://www.youtube.com/@Wankoros-japanese/videos",
    "data": []
  },
  {
    "title": "Yuka老師的日本語教室", 
    "url": "https://www.youtube.com/@yuka_japaneseteacher/videos",
    "data": []
  },
  {
    "title": "日文咩~醬咩", 
    "url": "https://www.youtube.com/@-rdip/videos",
    "data": []
  },
  {
    "title": "彩乃老師 / 日文 Podcast", 
    "url": "https://www.youtube.com/@am_japanese/videos",
    "data": []
  },
  {
    "title": "えびてんちゃんの日本語教室", 
    "url": "https://www.youtube.com/@ebitenchan/videos",
    "data": []
  }
]